README.rst
setup.py
aapippackage/__init__.py
aapippackage/__pkg__.py
aapippackage/text.py
aapippackage.egg-info/PKG-INFO
aapippackage.egg-info/SOURCES.txt
aapippackage.egg-info/dependency_links.txt
aapippackage.egg-info/not-zip-safe
aapippackage.egg-info/top_level.txt
aapippackage/dictionary/__init__.py
aapippackage/dictionary/helper.py
aapippackage/errors/NavitaireError.py
aapippackage/errors/PromotionError.py
aapippackage/errors/StationError.py
aapippackage/errors/ValuePackError.py
aapippackage/errors/__init__.py
aapippackage/tests/__init__.py
aapippackage/tests/test_dictutility.py
aapippackage/tests/test_text.py
aapippackage/validation/__init__.py
aapippackage/validation/validate.py