Metadata-Version: 1.0
Name: aapippackage
Version: 0.9
Summary: Utility Library
Home-page: UNKNOWN
Author: Gaurav Sharma
Author-email: gauravsharmaa@airasia.com
License: MIT
Platform: UNKNOWN
